networking_powervm/__init__.py
networking_powervm/_i18n.py
networking_powervm/version.py
networking_powervm/hacking/__init__.py
networking_powervm/hacking/checks.py
networking_powervm/locale/networking-powervm.pot
networking_powervm/locale/de/networking-powervm.po
networking_powervm/locale/es/networking-powervm.po
networking_powervm/locale/fr/networking-powervm.po
networking_powervm/locale/it/networking-powervm.po
networking_powervm/locale/ja/networking-powervm.po
networking_powervm/locale/ko/networking-powervm.po
networking_powervm/locale/pt-BR/networking-powervm.po
networking_powervm/locale/ru/networking-powervm.po
networking_powervm/locale/zh-Hans/networking-powervm.po
networking_powervm/locale/zh-Hant/networking-powervm.po
networking_powervm/plugins/__init__.py
networking_powervm/plugins/ibm/__init__.py
networking_powervm/plugins/ibm/agent/__init__.py
networking_powervm/plugins/ibm/agent/powervm/__init__.py
networking_powervm/plugins/ibm/agent/powervm/agent_base.py
networking_powervm/plugins/ibm/agent/powervm/constants.py
networking_powervm/plugins/ibm/agent/powervm/exceptions.py
networking_powervm/plugins/ibm/agent/powervm/powervm_sea_agent.rst
networking_powervm/plugins/ibm/agent/powervm/prov_req.py
networking_powervm/plugins/ibm/agent/powervm/sea_agent.py
networking_powervm/plugins/ibm/agent/powervm/sriov_agent.py
networking_powervm/plugins/ibm/agent/powervm/utils.py
networking_powervm/plugins/ml2/__init__.py
networking_powervm/plugins/ml2/drivers/__init__.py
networking_powervm/plugins/ml2/drivers/mech_pvm_base.py
networking_powervm/plugins/ml2/drivers/mech_pvm_sea.py
networking_powervm/plugins/ml2/drivers/mech_pvm_sriov.py
networking_powervm/tests/__init__.py
networking_powervm/tests/unit/__init__.py
networking_powervm/tests/unit/plugins/__init__.py
networking_powervm/tests/unit/plugins/ibm/__init__.py
networking_powervm/tests/unit/plugins/ibm/powervm/__init__.py
networking_powervm/tests/unit/plugins/ibm/powervm/base.py
networking_powervm-9.0.0.dist-info/AUTHORS
networking_powervm-9.0.0.dist-info/LICENSE
networking_powervm-9.0.0.dist-info/METADATA
networking_powervm-9.0.0.dist-info/WHEEL
networking_powervm-9.0.0.dist-info/entry_points.txt
networking_powervm-9.0.0.dist-info/pbr.json
networking_powervm-9.0.0.dist-info/top_level.txt
networking_powervm-9.0.0.dist-info/RECORD
