Metadata-Version: 2.1
Name: networking-powervm
Version: 9.0.0
Summary: PowerVM Neutron ML2 Agent for OpenStack Neutron.
Home-page: http://networking-powervm.readthedocs.io/en/latest/
Author: OpenStack
Author-email: openstack-discuss@lists.openstack.org
License: UNKNOWN
Platform: UNKNOWN
Classifier: Environment :: OpenStack
Classifier: Intended Audience :: Information Technology
Classifier: Intended Audience :: System Administrators
Classifier: License :: OSI Approved :: Apache Software License
Classifier: Operating System :: POSIX :: Linux
Classifier: Programming Language :: Python
Classifier: Programming Language :: Python :: 2
Classifier: Programming Language :: Python :: 2.7
Classifier: Programming Language :: Python :: 3
Classifier: Programming Language :: Python :: 3.7
Requires-Dist: amqp (!=2.1.4,>=2.1.1)
Requires-Dist: pbr (!=2.1.0,>=2.0.0)
Requires-Dist: Routes (>=2.3.1)
Requires-Dist: eventlet (!=0.18.3,!=0.20.1,>=0.18.2)
Requires-Dist: greenlet (>=0.4.10)
Requires-Dist: six (>=1.10.0)
Requires-Dist: oslo.log (>=3.36.0)
Requires-Dist: oslo.serialization (!=2.19.1,>=2.18.0)
Requires-Dist: oslo.service (!=1.28.1,>=1.24.0)
Requires-Dist: oslo.utils (>=3.33.0)
Requires-Dist: oslo.config (>=5.1.0)
Requires-Dist: pypowervm (>=1.1.11)
Requires-Dist: setuptools (!=24.0.0,!=34.0.0,!=34.0.1,!=34.0.2,!=34.0.3,!=34.1.0,!=34.1.1,!=34.2.0,!=34.3.0,!=34.3.1,!=34.3.2,!=36.2.0,>=21.0.0)
Requires-Dist: neutron-lib (>=1.18.0)
